haystack_integrations/components/retrievers/py.typed
haystack_integrations/components/retrievers/snowflake/__init__.py
haystack_integrations/components/retrievers/snowflake/auth.py
haystack_integrations/components/retrievers/snowflake/snowflake_table_retriever.py
snowflake_haystack-3.0.0.dist-info/METADATA
snowflake_haystack-3.0.0.dist-info/WHEEL
snowflake_haystack-3.0.0.dist-info/licenses/LICENSE.txt
snowflake_haystack-3.0.0.dist-info/RECORD
