Metadata-Version: 2.4
Name: snowflake-haystack
Version: 3.0.0
Summary: A Snowflake integration for the Haystack framework.
Project-URL: Documentation, https://github.com/deepset-ai/haystack-core-integrations/tree/main/integrations/snowflake#readme
Project-URL: Issues, https://github.com/deepset-ai/haystack-core-integrations/issues
Project-URL: Source, https://github.com/deepset-ai/haystack-core-integrations/tree/main/integrations/snowflake
Author-email: deepset GmbH <info@deepset.ai>, Mohamed Sriha <mohamed.sriha@deepset.ai>
License-Expression: Apache-2.0
License-File: LICENSE.txt
Classifier: Development Status :: 4 - Beta
Classifier: License :: OSI Approved :: Apache Software License
Classifier: Programming Language :: Python
Classifier: Programming Language :: Python :: 3.10
Classifier: Programming Language :: Python :: 3.11
Classifier: Programming Language :: Python :: 3.12
Classifier: Programming Language :: Python :: 3.13
Classifier: Programming Language :: Python :: Implementation :: CPython
Classifier: Programming Language :: Python :: Implementation :: PyPy
Requires-Python: >=3.10
Requires-Dist: adbc-driver-snowflake>=1.4.0
Requires-Dist: haystack-ai>=2.22.0
Requires-Dist: polars[pandas,pyarrow]>=1.23.0
Requires-Dist: snowflake-connector-python>=3.12.0
